{
  "actions": [
    {
      "acted_at": "2015-06-16", 
      "committees": [
        "HSWM"
      ], 
      "references": [], 
      "status": "REFERRED", 
      "text": "Referred to the House Committee on Ways and Means.", 
      "type": "referral"
    }
  ], 
  "amendments": [], 
  "bill_id": "hr2788-114", 
  "bill_type": "hr", 
  "by_request": false, 
  "committees": [
    {
      "activity": [
        "referral"
      ], 
      "committee": "House Ways and Means", 
      "committee_id": "HSWM"
    }
  ], 
  "congress": "114", 
  "cosponsors": [
    {
      "district": "3", 
      "name": "Kind, Ron", 
      "sponsored_at": "2015-06-16", 
      "state": "WI", 
      "thomas_id": "01498", 
      "title": "Rep", 
      "withdrawn_at": null
    }, 
    {
      "district": "24", 
      "name": "Marchant, Kenny", 
      "sponsored_at": "2015-06-17", 
      "state": "TX", 
      "thomas_id": "01806", 
      "title": "Rep", 
      "withdrawn_at": null
    }, 
    {
      "district": "3", 
      "name": "Paulsen, Erik", 
      "sponsored_at": "2015-07-07", 
      "state": "MN", 
      "thomas_id": "01930", 
      "title": "Rep", 
      "withdrawn_at": null
    }, 
    {
      "district": "16", 
      "name": "Renacci, James B.", 
      "sponsored_at": "2015-06-25", 
      "state": "OH", 
      "thomas_id": "02048", 
      "title": "Rep", 
      "withdrawn_at": null
    }, 
    {
      "district": "12", 
      "name": "Tiberi, Patrick J.", 
      "sponsored_at": "2015-06-18", 
      "state": "OH", 
      "thomas_id": "01664", 
      "title": "Rep", 
      "withdrawn_at": null
    }
  ], 
  "enacted_as": null, 
  "history": {
    "active": false, 
    "awaiting_signature": false, 
    "enacted": false, 
    "vetoed": false
  }, 
  "introduced_at": "2015-06-16", 
  "number": "2788", 
  "official_title": "To amend the Internal Revenue Code of 1986 to provide for S corporation reform, and for other purposes.", 
  "popular_title": null, 
  "related_bills": [
    {
      "bill_id": "hr629-114", 
      "reason": "related", 
      "type": "bill"
    }, 
    {
      "bill_id": "hr630-114", 
      "reason": "related", 
      "type": "bill"
    }, 
    {
      "bill_id": "s1905-114", 
      "reason": "related", 
      "type": "bill"
    }
  ], 
  "short_title": "S Corporation Modernization Act of 2015", 
  "sponsor": {
    "district": "8", 
    "name": "Reichert, David G.", 
    "state": "WA", 
    "thomas_id": "01810", 
    "title": "Rep", 
    "type": "person"
  }, 
  "status": "REFERRED", 
  "status_at": "2015-06-16", 
  "subjects": [
    "Accounting and auditing", 
    "Business investment and capital", 
    "Capital gains tax", 
    "Charitable contributions", 
    "Corporate finance and management", 
    "Employee benefits and pensions", 
    "Income tax deductions", 
    "Income tax exclusion", 
    "Securities", 
    "Small business", 
    "Tax administration and collection, taxpayers", 
    "Taxation"
  ], 
  "subjects_top_term": "Taxation", 
  "summary": {
    "as": "Introduced", 
    "date": "2015-06-16", 
    "text": "S Corporation Modernization Act of 2015\u00a0\n\nAmends the Internal Revenue Code to revise the tax treatment of S corporations by: (1) permanently reducing from 10 to 5 years the period during which S corporation built-in gains are subject to tax, (2) repealing mandatory termination of S corporation elections for excessive passive investment income, (3) allowing S corporations to increase passive investment income from 25 to 60% without incurring additional tax, (4) allowing nonresident aliens to be potential current beneficiaries of an electing small business trust (ESBT), (5) allowing individual retirement accounts to be S corporation shareholders, (6) allowing ESBTs to claim expanded charitable tax deductions, and (7) making permanent the rule requiring a basis adjustment to stock of an S corporation making charitable contributions of property."
  }, 
  "titles": [
    {
      "as": "introduced", 
      "is_for_portion": false, 
      "title": "S Corporation Modernization Act of 2015", 
      "type": "short"
    }, 
    {
      "as": "introduced", 
      "is_for_portion": false, 
      "title": "To amend the Internal Revenue Code of 1986 to provide for S corporation reform, and for other purposes.", 
      "type": "official"
    }
  ], 
  "updated_at": "2016-06-25T06:46:59-04:00", 
  "url": "http://thomas.loc.gov/cgi-bin/bdquery/z?d114:HR2788:@@@L&summ2=m&"
}