{
  "actions": [
    {
      "acted_at": "2015-12-01", 
      "committees": [
        "HSED"
      ], 
      "references": [], 
      "status": "REFERRED", 
      "text": "Referred to the House Committee on Education and the Workforce.", 
      "type": "referral"
    }
  ], 
  "amendments": [], 
  "bill_id": "hr4146-114", 
  "bill_type": "hr", 
  "by_request": false, 
  "committees": [
    {
      "activity": [
        "referral"
      ], 
      "committee": "House Education and the Workforce", 
      "committee_id": "HSED"
    }
  ], 
  "congress": "114", 
  "cosponsors": [
    {
      "district": "7", 
      "name": "Capuano, Michael E.", 
      "sponsored_at": "2016-05-11", 
      "state": "MA", 
      "thomas_id": "01564", 
      "title": "Rep", 
      "withdrawn_at": null
    }, 
    {
      "district": "9", 
      "name": "Pascrell, Bill, Jr.", 
      "sponsored_at": "2016-05-11", 
      "state": "NJ", 
      "thomas_id": "01510", 
      "title": "Rep", 
      "withdrawn_at": null
    }, 
    {
      "district": "52", 
      "name": "Peters, Scott H.", 
      "sponsored_at": "2016-02-08", 
      "state": "CA", 
      "thomas_id": "02113", 
      "title": "Rep", 
      "withdrawn_at": null
    }, 
    {
      "district": "13", 
      "name": "Ryan, Tim", 
      "sponsored_at": "2016-02-02", 
      "state": "OH", 
      "thomas_id": "01756", 
      "title": "Rep", 
      "withdrawn_at": null
    }
  ], 
  "enacted_as": null, 
  "history": {
    "active": false, 
    "awaiting_signature": false, 
    "enacted": false, 
    "vetoed": false
  }, 
  "introduced_at": "2015-12-01", 
  "number": "4146", 
  "official_title": "To authorize the Secretary of Education to provide grants for education programs on the history of the treatment of Italian Americans during World War II.", 
  "popular_title": null, 
  "related_bills": [], 
  "short_title": null, 
  "sponsor": {
    "district": "19", 
    "name": "Lofgren, Zoe", 
    "state": "CA", 
    "thomas_id": "00701", 
    "title": "Rep", 
    "type": "person"
  }, 
  "status": "REFERRED", 
  "status_at": "2015-12-01", 
  "subjects": [
    "Civil rights and liberties, minority issues", 
    "Conflicts and wars", 
    "Education programs funding", 
    "Europe", 
    "Italy", 
    "Racial and ethnic relations", 
    "U.S. history"
  ], 
  "subjects_top_term": "Civil rights and liberties, minority issues", 
  "summary": {
    "as": "Introduced", 
    "date": "2015-12-01", 
    "text": "This bill authorizes the Department of Education to provide grants for public awareness education programs on the history of the treatment of Italian Americans during World War II.\n\nIn awarding such grants, priority shall be given to Italian American historical and cultural organizations."
  }, 
  "titles": [
    {
      "as": "introduced", 
      "is_for_portion": false, 
      "title": "To authorize the Secretary of Education to provide grants for education programs on the history of the treatment of Italian Americans during World War II.", 
      "type": "official"
    }
  ], 
  "updated_at": "2016-06-25T06:58:20-04:00", 
  "url": "http://thomas.loc.gov/cgi-bin/bdquery/z?d114:HR4146:@@@L&summ2=m&"
}