{
  "actions": [
    {
      "acted_at": "2015-07-23", 
      "committees": [
        "HSED"
      ], 
      "references": [], 
      "status": "REFERRED", 
      "text": "Referred to the House Committee on Education and the Workforce.", 
      "type": "referral"
    }, 
    {
      "acted_at": "2015-11-16", 
      "in_committee": null, 
      "references": [], 
      "text": "Referred to the Subcommittee on Higher Education and Workforce Training.", 
      "type": "referral"
    }
  ], 
  "amendments": [], 
  "bill_id": "hr3177-114", 
  "bill_type": "hr", 
  "by_request": false, 
  "committees": [
    {
      "activity": [
        "referral"
      ], 
      "committee": "House Education and the Workforce", 
      "committee_id": "HSED"
    }, 
    {
      "activity": [
        "referral"
      ], 
      "committee": "House Education and the Workforce", 
      "committee_id": "HSED", 
      "subcommittee": "Subcommittee on Higher Education and Workforce Training", 
      "subcommittee_id": "13"
    }
  ], 
  "congress": "114", 
  "cosponsors": [
    {
      "district": "11", 
      "name": "Barletta, Lou", 
      "sponsored_at": "2015-11-17", 
      "state": "PA", 
      "thomas_id": "02054", 
      "title": "Rep", 
      "withdrawn_at": null
    }, 
    {
      "district": "1", 
      "name": "Bonamici, Suzanne", 
      "sponsored_at": "2015-07-23", 
      "state": "OR", 
      "thomas_id": "02092", 
      "title": "Rep", 
      "withdrawn_at": null
    }, 
    {
      "district": "8", 
      "name": "Bucshon, Larry", 
      "sponsored_at": "2015-07-23", 
      "state": "IN", 
      "thomas_id": "02018", 
      "title": "Rep", 
      "withdrawn_at": null
    }, 
    {
      "district": "5", 
      "name": "Clark, Katherine M.", 
      "sponsored_at": "2015-07-23", 
      "state": "MA", 
      "thomas_id": "02196", 
      "title": "Rep", 
      "withdrawn_at": null
    }, 
    {
      "district": "53", 
      "name": "Davis, Susan A.", 
      "sponsored_at": "2015-07-23", 
      "state": "CA", 
      "thomas_id": "01641", 
      "title": "Rep", 
      "withdrawn_at": null
    }, 
    {
      "district": "11", 
      "name": "DeSaulnier, Mark", 
      "sponsored_at": "2015-07-23", 
      "state": "CA", 
      "thomas_id": "02227", 
      "title": "Rep", 
      "withdrawn_at": null
    }, 
    {
      "district": "10", 
      "name": "Dold, Robert J.", 
      "sponsored_at": "2015-09-30", 
      "state": "IL", 
      "thomas_id": "02013", 
      "title": "Rep", 
      "withdrawn_at": null
    }, 
    {
      "district": "3", 
      "name": "Grijalva, Raul M.", 
      "sponsored_at": "2015-07-23", 
      "state": "AZ", 
      "thomas_id": "01708", 
      "title": "Rep", 
      "withdrawn_at": null
    }, 
    {
      "district": "6", 
      "name": "Grothman, Glenn", 
      "sponsored_at": "2015-07-23", 
      "state": "WI", 
      "thomas_id": "02276", 
      "title": "Rep", 
      "withdrawn_at": null
    }, 
    {
      "district": "3", 
      "name": "Herrera Beutler, Jaime", 
      "sponsored_at": "2015-09-17", 
      "state": "WA", 
      "thomas_id": "02071", 
      "title": "Rep", 
      "withdrawn_at": null
    }, 
    {
      "district": "9", 
      "name": "Keating, William R.", 
      "sponsored_at": "2015-10-20", 
      "state": "MA", 
      "thomas_id": "02025", 
      "title": "Rep", 
      "withdrawn_at": null
    }, 
    {
      "district": "3", 
      "name": "Kelly, Mike", 
      "sponsored_at": "2015-07-23", 
      "state": "PA", 
      "thomas_id": "02051", 
      "title": "Rep", 
      "withdrawn_at": null
    }, 
    {
      "district": "2", 
      "name": "Kline, John", 
      "sponsored_at": "2015-07-23", 
      "state": "MN", 
      "thomas_id": "01733", 
      "title": "Rep", 
      "withdrawn_at": null
    }, 
    {
      "district": "33", 
      "name": "Lieu, Ted", 
      "sponsored_at": "2016-05-10", 
      "state": "CA", 
      "thomas_id": "02230", 
      "title": "Rep", 
      "withdrawn_at": null
    }, 
    {
      "district": "3", 
      "name": "MacArthur, Thomas", 
      "sponsored_at": "2015-09-17", 
      "state": "NJ", 
      "thomas_id": "02258", 
      "title": "Rep", 
      "withdrawn_at": null
    }, 
    {
      "district": "6", 
      "name": "Messer, Luke", 
      "sponsored_at": "2015-07-23", 
      "state": "IN", 
      "thomas_id": "02130", 
      "title": "Rep", 
      "withdrawn_at": null
    }, 
    {
      "district": "1", 
      "name": "Norcross, Donald", 
      "sponsored_at": "2015-09-18", 
      "state": "NJ", 
      "thomas_id": "02202", 
      "title": "Rep", 
      "withdrawn_at": null
    }, 
    {
      "district": "52", 
      "name": "Peters, Scott H.", 
      "sponsored_at": "2016-02-04", 
      "state": "CA", 
      "thomas_id": "02113", 
      "title": "Rep", 
      "withdrawn_at": null
    }, 
    {
      "district": "2", 
      "name": "Pocan, Mark", 
      "sponsored_at": "2015-07-23", 
      "state": "WI", 
      "thomas_id": "02171", 
      "title": "Rep", 
      "withdrawn_at": null
    }, 
    {
      "district": "2", 
      "name": "Polis, Jared", 
      "sponsored_at": "2015-07-23", 
      "state": "CO", 
      "thomas_id": "01910", 
      "title": "Rep", 
      "withdrawn_at": null
    }, 
    {
      "district": "1", 
      "name": "Roe, David P.", 
      "sponsored_at": "2015-07-23", 
      "state": "TN", 
      "thomas_id": "01954", 
      "title": "Rep", 
      "withdrawn_at": null
    }, 
    {
      "district": "39", 
      "name": "Royce, Edward R.", 
      "sponsored_at": "2015-07-23", 
      "state": "CA", 
      "thomas_id": "00998", 
      "title": "Rep", 
      "withdrawn_at": null
    }, 
    {
      "district": null, 
      "name": "Sablan, Gregorio Kilili Camacho", 
      "sponsored_at": "2015-07-23", 
      "state": "MP", 
      "thomas_id": "01962", 
      "title": "Rep", 
      "withdrawn_at": null
    }, 
    {
      "district": "3", 
      "name": "Scott, Robert C. \"Bobby\"", 
      "sponsored_at": "2015-07-23", 
      "state": "VA", 
      "thomas_id": "01037", 
      "title": "Rep", 
      "withdrawn_at": null
    }, 
    {
      "district": "21", 
      "name": "Stefanik, Elise M.", 
      "sponsored_at": "2015-07-23", 
      "state": "NY", 
      "thomas_id": "02263", 
      "title": "Rep", 
      "withdrawn_at": null
    }, 
    {
      "district": "41", 
      "name": "Takano, Mark", 
      "sponsored_at": "2015-07-23", 
      "state": "CA", 
      "thomas_id": "02110", 
      "title": "Rep", 
      "withdrawn_at": null
    }, 
    {
      "district": "7", 
      "name": "Walberg, Tim", 
      "sponsored_at": "2015-07-23", 
      "state": "MI", 
      "thomas_id": "01855", 
      "title": "Rep", 
      "withdrawn_at": null
    }, 
    {
      "district": "2", 
      "name": "Walden, Greg", 
      "sponsored_at": "2016-02-29", 
      "state": "OR", 
      "thomas_id": "01596", 
      "title": "Rep", 
      "withdrawn_at": null
    }, 
    {
      "district": null, 
      "name": "Welch, Peter", 
      "sponsored_at": "2015-09-08", 
      "state": "VT", 
      "thomas_id": "01879", 
      "title": "Rep", 
      "withdrawn_at": null
    }
  ], 
  "enacted_as": null, 
  "history": {
    "active": false, 
    "awaiting_signature": false, 
    "enacted": false, 
    "vetoed": false
  }, 
  "introduced_at": "2015-07-23", 
  "number": "3177", 
  "official_title": "To simplify the application used for the estimation and determination of financial aid eligibility for postsecondary education.", 
  "popular_title": null, 
  "related_bills": [], 
  "short_title": "Simplifying the Application for Student Aid Act", 
  "sponsor": {
    "district": "3", 
    "name": "Heck, Joseph J.", 
    "state": "NV", 
    "thomas_id": "02040", 
    "title": "Rep", 
    "type": "person"
  }, 
  "status": "REFERRED", 
  "status_at": "2015-07-23", 
  "subjects": [
    "Education", 
    "Higher education", 
    "Student aid and college costs", 
    "Tax administration and collection, taxpayers"
  ], 
  "subjects_top_term": "Education", 
  "summary": {
    "as": "Introduced", 
    "date": "2015-07-23", 
    "text": "Simplifying the Application for Student Aid Act\n\nThis bill amends title IV (Student Assistance) of the Higher Education Act of 1965 to require the Department of Education to provide for the use of tax information from the second preceding tax year (the \"prior, prior year\") to determine a student's financial aid eligibility. It requires data sharing between the Internal Revenue Service and the Department of Education, pursuant to taxpayer consent."
  }, 
  "titles": [
    {
      "as": "introduced", 
      "is_for_portion": false, 
      "title": "Simplifying the Application for Student Aid Act", 
      "type": "short"
    }, 
    {
      "as": "introduced", 
      "is_for_portion": false, 
      "title": "To simplify the application used for the estimation and determination of financial aid eligibility for postsecondary education.", 
      "type": "official"
    }
  ], 
  "updated_at": "2016-06-25T06:50:14-04:00", 
  "url": "http://thomas.loc.gov/cgi-bin/bdquery/z?d114:HR3177:@@@L&summ2=m&"
}