{
  "actions": [
    {
      "acted_at": "2015-05-20", 
      "committees": [
        "HSII"
      ], 
      "references": [], 
      "status": "REFERRED", 
      "text": "Referred to the House Committee on Natural Resources.", 
      "type": "referral"
    }, 
    {
      "acted_at": "2015-06-10", 
      "in_committee": null, 
      "references": [], 
      "text": "Referred to the Subcommittee on Federal Lands.", 
      "type": "referral"
    }
  ], 
  "amendments": [], 
  "bill_id": "hr2467-114", 
  "bill_type": "hr", 
  "by_request": false, 
  "committees": [
    {
      "activity": [
        "referral"
      ], 
      "committee": "House Natural Resources", 
      "committee_id": "HSII"
    }, 
    {
      "activity": [
        "referral"
      ], 
      "committee": "House Natural Resources", 
      "committee_id": "HSII", 
      "subcommittee": "Subcommittee on Federal Lands", 
      "subcommittee_id": "10"
    }
  ], 
  "congress": "114", 
  "cosponsors": [
    {
      "district": "5", 
      "name": "Brooks, Mo", 
      "sponsored_at": "2015-05-20", 
      "state": "AL", 
      "thomas_id": "01987", 
      "title": "Rep", 
      "withdrawn_at": null
    }, 
    {
      "district": "4", 
      "name": "Fleming, John", 
      "sponsored_at": "2015-05-20", 
      "state": "LA", 
      "thomas_id": "01924", 
      "title": "Rep", 
      "withdrawn_at": null
    }, 
    {
      "district": "4", 
      "name": "Gosar, Paul A.", 
      "sponsored_at": "2015-05-20", 
      "state": "AZ", 
      "thomas_id": "01992", 
      "title": "Rep", 
      "withdrawn_at": null
    }, 
    {
      "district": "8", 
      "name": "Hudson, Richard", 
      "sponsored_at": "2015-05-20", 
      "state": "NC", 
      "thomas_id": "02140", 
      "title": "Rep", 
      "withdrawn_at": null
    }, 
    {
      "district": "1", 
      "name": "Labrador, Raul R.", 
      "sponsored_at": "2015-10-09", 
      "state": "ID", 
      "thomas_id": "02011", 
      "title": "Rep", 
      "withdrawn_at": null
    }, 
    {
      "district": "1", 
      "name": "LaMalfa, Doug", 
      "sponsored_at": "2015-05-20", 
      "state": "CA", 
      "thomas_id": "02100", 
      "title": "Rep", 
      "withdrawn_at": null
    }, 
    {
      "district": "5", 
      "name": "Lamborn, Doug", 
      "sponsored_at": "2015-05-20", 
      "state": "CO", 
      "thomas_id": "01834", 
      "title": "Rep", 
      "withdrawn_at": null
    }, 
    {
      "district": null, 
      "name": "Lummis, Cynthia M.", 
      "sponsored_at": "2015-05-20", 
      "state": "WY", 
      "thomas_id": "01960", 
      "title": "Rep", 
      "withdrawn_at": null
    }, 
    {
      "district": "19", 
      "name": "Neugebauer, Randy", 
      "sponsored_at": "2015-05-20", 
      "state": "TX", 
      "thomas_id": "01758", 
      "title": "Rep", 
      "withdrawn_at": null
    }, 
    {
      "district": "8", 
      "name": "Posey, Bill", 
      "sponsored_at": "2015-05-20", 
      "state": "FL", 
      "thomas_id": "01915", 
      "title": "Rep", 
      "withdrawn_at": null
    }, 
    {
      "district": "6", 
      "name": "Schweikert, David", 
      "sponsored_at": "2015-05-20", 
      "state": "AZ", 
      "thomas_id": "01994", 
      "title": "Rep", 
      "withdrawn_at": null
    }, 
    {
      "district": "2", 
      "name": "Stewart, Chris", 
      "sponsored_at": "2015-05-20", 
      "state": "UT", 
      "thomas_id": "02168", 
      "title": "Rep", 
      "withdrawn_at": null
    }, 
    {
      "district": "2", 
      "name": "Wenstrup, Brad R.", 
      "sponsored_at": "2015-05-20", 
      "state": "OH", 
      "thomas_id": "02152", 
      "title": "Rep", 
      "withdrawn_at": null
    }
  ], 
  "enacted_as": null, 
  "history": {
    "active": false, 
    "awaiting_signature": false, 
    "enacted": false, 
    "vetoed": false
  }, 
  "introduced_at": "2015-05-20", 
  "number": "2467", 
  "official_title": "To clarify that the Secretary of Homeland Security may undertake law enforcement and border security activities within the Organ Mountains-Desert Peaks National Monument, and for other purposes.", 
  "popular_title": null, 
  "related_bills": [], 
  "short_title": "Organ Mountains-Desert Peaks National Monument Correction Act", 
  "sponsor": {
    "district": "2", 
    "name": "Pearce, Stevan", 
    "state": "NM", 
    "thomas_id": "01738", 
    "title": "Rep", 
    "type": "person"
  }, 
  "status": "REFERRED", 
  "status_at": "2015-05-20", 
  "subjects": [
    "Aviation and airports", 
    "Border security and unlawful immigration", 
    "Land use and conservation", 
    "Law enforcement administration and funding", 
    "Military education and training", 
    "Monuments and memorials", 
    "Motor vehicles", 
    "New Mexico", 
    "Public lands and natural resources", 
    "Terrorism", 
    "Wilderness and natural areas, wildlife refuges, wild rivers, habitats"
  ], 
  "subjects_top_term": "Public lands and natural resources", 
  "summary": {
    "as": "Introduced", 
    "date": "2015-05-20", 
    "text": "Organ Mountains-Desert Peaks National Monument Correction Act\n\n Prohibits construing either the national monument designation or any management plan in furtherance of the Organ Mountains-Desert Peaks National Monument, New Mexico (designated on May 21, 2014) as:\n\n preventing the Department of Homeland Security (DHS) from undertaking law enforcement and border security activities within the areas designated as the Monument, including the ability to use motorized vehicles within it; limiting the 2006 Memorandum of Understanding among DHS, the Department of the Interior, and the Department of Agriculture regarding cooperative national security and counterterrorism efforts on federal land along U.S. borders; preventing DHS from conducting low-level overflights over the Monument for law enforcement and border security purposes; or preventing Interior from allowing within the Monument the installation and maintenance of communication or surveillance infrastructure necessary for law enforcement or border security activities. Makes the route excluded from the Potrillo Mountains, identified as \"Restricted--Administrative Access\" on the map entitled \"Potrillo Mountains Complex,\" dated December 10, 2013, available for administrative and law enforcement uses, including border security activities."
  }, 
  "titles": [
    {
      "as": "introduced", 
      "is_for_portion": false, 
      "title": "Organ Mountains-Desert Peaks National Monument Correction Act", 
      "type": "short"
    }, 
    {
      "as": "introduced", 
      "is_for_portion": false, 
      "title": "To clarify that the Secretary of Homeland Security may undertake law enforcement and border security activities within the Organ Mountains-Desert Peaks National Monument, and for other purposes.", 
      "type": "official"
    }
  ], 
  "updated_at": "2016-06-25T06:44:10-04:00", 
  "url": "http://thomas.loc.gov/cgi-bin/bdquery/z?d114:HR2467:@@@L&summ2=m&"
}